Workbook

Sheet Supuestos
A1: Supuestos del modelo (editables en azul)
A3: Categoría | B3: Concepto | C3: Valor | D3: Unidad
A4: WhatsApp | B4: Coste conversación servicio (iniciada por usuario) | C4: 0 | D4: €/msg
A5: WhatsApp | B5: Coste conversación marketing (saliente España) | C5: 0.035 | D5: €/msg
A6: WhatsApp | B6: Alta número Twilio (opcional) | C6: 1 | D6: €/mes
A7: LLM | B7: Coste gpt-4o-mini por 1.000 mensajes (≈500 tokens) | C7: 0.15 | D7: €/1.000 msg
A8: Whisper (STT) | B8: Coste por minuto transcripción | C8: 0.006 | D8: €/min audio
A9: ElevenLabs TTS | B9: Coste por minuto audio generado (nota voz) | C9: 0.075 | D9: €/min
A10: ElevenLabs Agent | B10: Coste agente conversacional por minuto | C10: 0.085 | D10: €/min
A11: Twilio Voice | B11: Llamada entrante número local España | C11: 0.013 | D11: €/min
A12: Google Calendar API | B12: Dentro de cuota gratuita | C12: 0 | D12: €/mes
A13: Hosting Railway | B13: Plan gratis hasta X horas → Hobby | C13: 5 | D13: €/mes
A14: Sentry (errores) | B14: Plan gratis | C14: 0 | D14: €/mes
A15: Dominio (opcional) | B15: .es anual prorrateado | C15: 0.8 | D15: €/mes
A18: Fuente precios: investigación web 21-abr-2026 (ElevenLabs, Twilio, Meta). Revisar trimestralmente.

Sheet Escenarios
A1: Escenarios de coste mensual por fase del proyecto
A3: Concepto | B3: Fase 1 MVP | C3: Fase 2 Voz asinc. | D3: Fase 3 Llamada | E3: Fase 4 Piloto real | F3: Fase 5 (10 clientes) | G3: Notas
A4: Mensajes entrantes/mes | B4: 50 | C4: 200 | D4: 400 | E4: 1500 | F4: 15000 | G4: Ajustable
A5: Notas de voz in/mes (2 min cada) | B5: 0 | C5: 40 | D5: 60 | E5: 150 | F5: 1500 | G5: Ajustable
A6: Minutos llamada voz/mes | B6: 0 | C6: 0 | D6: 30 | E6: 120 | F6: 1500 | G6: Ajustable
A7: Mensajes salientes marketing/mes | B7: 0 | C7: 0 | D7: 0 | E7: 50 | F7: 800 | G7: Ajustable
A9: Costes derivados
A10: LLM (texto) | B10: =(B4/1000)*Supuestos!$C$7 -> 0.0075 | C10: =(C4/1000)*Supuestos!$C$7 -> 0.03 | D10: =(D4/1000)*Supuestos!$C$7 -> 0.06 | E10: =(E4/1000)*Supuestos!$C$7 -> 0.225 | F10: =(F4/1000)*Supuestos!$C$7 -> 2.25
A11: Whisper (transcripción notas voz) | B11: =B5*2*Supuestos!$C$8 -> 0 | C11: =C5*2*Supuestos!$C$8 -> 0.48 | D11: =D5*2*Supuestos!$C$8 -> 0.72 | E11: =E5*2*Supuestos!$C$8 -> 1.8 | F11: =F5*2*Supuestos!$C$8 -> 18
A12: ElevenLabs TTS (respuestas voz async) | B12: =B5*0.5*Supuestos!$C$9 -> 0 | C12: =C5*0.5*Supuestos!$C$9 -> 1.5 | D12: =D5*0.5*Supuestos!$C$9 -> 2.25 | E12: =E5*0.5*Supuestos!$C$9 -> 5.625 | F12: =F5*0.5*Supuestos!$C$9 -> 56.25
A13: ElevenLabs Conversational Agent | B13: =B6*Supuestos!$C$10 -> 0 | C13: =C6*Supuestos!$C$10 -> 0 | D13: =D6*Supuestos!$C$10 -> 2.55 | E13: =E6*Supuestos!$C$10 -> 10.2 | F13: =F6*Supuestos!$C$10 -> 127.5
A14: Twilio Voice (minutos) | B14: =B6*Supuestos!$C$11 -> 0 | C14: =C6*Supuestos!$C$11 -> 0 | D14: =D6*Supuestos!$C$11 -> 0.39 | E14: =E6*Supuestos!$C$11 -> 1.56 | F14: =F6*Supuestos!$C$11 -> 19.5
A15: Twilio número alta | B15: =IF(B6>0,Supuestos!$C$6,0) -> 0 | C15: =IF(C6>0,Supuestos!$C$6,0) -> 0 | D15: =IF(D6>0,Supuestos!$C$6,0) -> 1 | E15: =IF(E6>0,Supuestos!$C$6,0) -> 1 | F15: =IF(F6>0,Supuestos!$C$6,0) -> 1
A16: WhatsApp marketing (salientes) | B16: =B7*Supuestos!$C$5 -> 0 | C16: =C7*Supuestos!$C$5 -> 0 | D16: =D7*Supuestos!$C$5 -> 0 | E16: =E7*Supuestos!$C$5 -> 1.75 | F16: =F7*Supuestos!$C$5 -> 28
A17: Hosting (Railway) | B17: =IF(B6>0,Supuestos!$C$13,0) -> 0 | C17: =IF(C6>0,Supuestos!$C$13,0) -> 0 | D17: =IF(D6>0,Supuestos!$C$13,0) -> 5 | E17: =IF(E6>0,Supuestos!$C$13,0) -> 5 | F17: =IF(F6>0,Supuestos!$C$13,0) -> 5
A18: Dominio | B18: =IF(B7>0,Supuestos!$C$15,0) -> 0 | C18: =IF(C7>0,Supuestos!$C$15,0) -> 0 | D18: =IF(D7>0,Supuestos!$C$15,0) -> 0 | E18: =IF(E7>0,Supuestos!$C$15,0) -> 0.8 | F18: =IF(F7>0,Supuestos!$C$15,0) -> 0.8
A19: TOTAL €/mes | B19: =SUM(B10:B18) -> 0.0075 | C19: =SUM(C10:C18) -> 2.01 | D19: =SUM(D10:D18) -> 11.97 | E19: =SUM(E10:E18) -> 27.96 | F19: =SUM(F10:F18) -> 258.3
A21: TOTAL anualizado | B21: =B19*12 -> 0.09 | C21: =C19*12 -> 24.12 | D21: =D19*12 -> 143.64 | E21: =E19*12 -> 335.52 | F21: =F19*12 -> 3099.6
A23: Coste por mensaje (€) | B23: =IFERROR(B19/B4,0) -> 0.00015 | C23: =IFERROR(C19/C4,0) -> 0.01005 | D23: =IFERROR(D19/D4,0) -> 0.029925 | E23: =IFERROR(E19/E4,0) -> 0.01864 | F23: =IFERROR(F19/F4,0) -> 0.01722
A26: Leyenda de colores:
A27: • Azul = input (editable)
A28: • Negro = fórmula calculada
A29: • Verde = enlace a otra hoja

Sheet Pricing cliente
A1: Propuesta de precios para clientes (negocios finales)
A3: Plan | B3: Incluye | C3: Precio €/mes | D3: Margen estimado | E3: Público
A4: Starter (texto) | B4: WhatsApp texto + Calendar + 1.500 msg | C4: 39 | D4: 0.8 | E4: Peluquerías solas
A5: Pro (voz asíncrona) | B5: Texto + notas de voz + 1.500 msg + 100 min TTS | C5: 79 | D5: 0.75 | E5: Peluquerías activas, estudios
A6: Premium (llamada) | B6: Todo Pro + número con IA + 200 min llamada | C6: 149 | D6: 0.65 | E6: Hoteles, clínicas
A7: Enterprise | B7: Multi-local, PMS, custom integrations | C7: 349 | D7: 0.55 | E7: Cadenas, grupos hoteleros
A10: Proyección ingresos (editar número de clientes)
A12: Plan | B12: Clientes | C12: Ingreso/mes | D12: Margen bruto/mes | E12: Margen anual
A13: Starter (texto) | B13: 2 | C13: =B13*C4 -> 78 | D13: =C13*D4 -> 62.4 | E13: =D13*12 -> 748.8
A14: Pro (voz asíncrona) | B14: 3 | C14: =B14*C5 -> 237 | D14: =C14*D5 -> 177.75 | E14: =D14*12 -> 2133
A15: Premium (llamada) | B15: 1 | C15: =B15*C6 -> 149 | D15: =C15*D6 -> 96.85 | E15: =D15*12 -> 1162.2
A16: Enterprise | B16: 0 | C16: =B16*C7 -> 0 | D16: =C16*D7 -> 0 | E16: =D16*12 -> 0
A17: TOTAL | B17: =SUM(B13:B16) -> 6 | C17: =SUM(C13:C16) -> 464 | D17: =SUM(D13:D16) -> 337 | E17: =SUM(E13:E16) -> 4044
